CHANGELOG.txt
LICENCE.txt
MANIFEST.in
README.txt
USE.txt
setup.py
fisikaSMA/__init__.py
fisikaSMA/kelas10.py
fisikaSMA/kelas11.py
fisikaSMA/kelas12.py
fisikaSMA.egg-info/PKG-INFO
fisikaSMA.egg-info/SOURCES.txt
fisikaSMA.egg-info/dependency_links.txt
fisikaSMA.egg-info/top_level.txt