Metadata-Version: 2.1
Name: fisikaSMA
Version: 0.0.3
Summary: Phisics Function
Home-page: 
Author: KS2_Kelompok 1
Author-email: 
License: MIT
Keywords: fisika
License-File: LICENCE.txt
